odoo/addons/hr_timesheet_sheet_warning/README.rst
odoo/addons/hr_timesheet_sheet_warning/__init__.py
odoo/addons/hr_timesheet_sheet_warning/__manifest__.py
odoo/addons/hr_timesheet_sheet_warning/i18n/es.po
odoo/addons/hr_timesheet_sheet_warning/i18n/hr_timesheet_sheet_warning.pot
odoo/addons/hr_timesheet_sheet_warning/i18n/it.po
odoo/addons/hr_timesheet_sheet_warning/models/__init__.py
odoo/addons/hr_timesheet_sheet_warning/models/hr_timesheet_sheet.py
odoo/addons/hr_timesheet_sheet_warning/models/hr_timesheet_sheet_warning_definition.py
odoo/addons/hr_timesheet_sheet_warning/models/hr_timesheet_sheet_warning_item.py
odoo/addons/hr_timesheet_sheet_warning/readme/CONTRIBUTORS.md
odoo/addons/hr_timesheet_sheet_warning/readme/DESCRIPTION.md
odoo/addons/hr_timesheet_sheet_warning/readme/INSTALL.md
odoo/addons/hr_timesheet_sheet_warning/readme/USAGE.md
odoo/addons/hr_timesheet_sheet_warning/security/hr_timesheet_sheet_warning_rules.xml
odoo/addons/hr_timesheet_sheet_warning/security/ir.model.access.csv
odoo/addons/hr_timesheet_sheet_warning/static/description/icon.png
odoo/addons/hr_timesheet_sheet_warning/static/description/index.html
odoo/addons/hr_timesheet_sheet_warning/tests/__init__.py
odoo/addons/hr_timesheet_sheet_warning/tests/test_hr_timesheet_sheet_warning.py
odoo/addons/hr_timesheet_sheet_warning/views/hr_timesheet_sheet.xml
odoo/addons/hr_timesheet_sheet_warning/views/hr_timesheet_sheet_warning_definition.xml
odoo/addons/hr_timesheet_sheet_warning/views/hr_timesheet_sheet_warning_item.xml
odoo_addon_hr_timesheet_sheet_warning-18.0.1.0.0.5.dist-info/METADATA
odoo_addon_hr_timesheet_sheet_warning-18.0.1.0.0.5.dist-info/WHEEL
odoo_addon_hr_timesheet_sheet_warning-18.0.1.0.0.5.dist-info/top_level.txt
odoo_addon_hr_timesheet_sheet_warning-18.0.1.0.0.5.dist-info/RECORD
